eegraph/__init__.py
eegraph/graph.py
eegraph/importData.py
eegraph/modelateData.py
eegraph/strategy.py
eegraph/tools.py
EEGRAPH-0.1.17.dist-info/LICENSE
EEGRAPH-0.1.17.dist-info/METADATA
EEGRAPH-0.1.17.dist-info/WHEEL
EEGRAPH-0.1.17.dist-info/top_level.txt
EEGRAPH-0.1.17.dist-info/RECORD
