Metadata-Version: 2.1
Name: EEGRAPH
Version: 0.1.17
Summary: UNKNOWN
Home-page: https://github.com/ufvceiec/EEGRAPH
Author: CEIEC
License: GPL-3.0
Platform: UNKNOWN
License-File: LICENSE
Requires-Dist: numpy (==1.21.1)
Requires-Dist: pandas (>=1.1.5)
Requires-Dist: mne (==1.2)
Requires-Dist: networkx (>=2.5)
Requires-Dist: plotly (>=4.14.3)
Requires-Dist: scipy (>=1.1.0)
Requires-Dist: scot (==0.2.1)
Requires-Dist: antropy (>=0.1.4)
Requires-Dist: kaleido (==0.2.1)
